{"tc":"TC2611","typhoonNumber":"2609","issue":"2026-07-13T12:45:00Z","forecast":[{"part":"title","issue":{"JST":"2026-07-13T21:45:00+09:00","UTC":"2026-07-13T12:45:00Z"},"typhoonNumber":"2609","name":{"jp":"バービー","en":"Bavi"}},{"part":{"jp":"実況","en":"Analysis"},"advancedHours":0,"validtime":{"JST":"2026-07-13T21:00:00+09:00","UTC":"2026-07-13T12:00:00Z"},"track":{"preTyphoon":[[9.5,162.6],[9.1,162.4],[9.7,161.8],[10.2,161.7],[10.2,161.5],[10.8,161.2],[10.8,160.6],[10.6,160.2],[10.3,159.9]],"typhoon":[[10.3,159.9],[11.1,159.7],[11.9,159.4],[12.3,158.3],[12.3,157.9],[12.3,157.3],[12.7,156.8],[12.6,156.3],[12.8,155.6],[12.9,154.8],[12.9,154.2],[12.9,153.6],[12.8,153.1],[12.7,152.8],[12.7,152.3],[12.7,151.9],[12.5,151.5],[12.5,151.2],[12.5,150.9],[12.6,150.7],[12.7,150.3],[12.7,149.8],[12.7,149.6],[12.8,149.2],[12.8,149],[13.1,148.7],[13.5,148.1],[13.6,147.6],[13.8,147],[13.7,146.5],[14,146.1],[14.2,145.6],[14.3,145.1],[14.6,144.6],[14.9,144],[15.1,143.4],[15.5,142.8],[15.8,141.9],[15.9,141.1],[16.1,140.5],[16.2,140],[16.3,139.2],[16.5,138.4],[16.8,137.6],[16.8,136.7],[16.8,136],[16.8,135.3],[16.9,134.9],[17,134.1],[16.9,133.5],[16.9,133],[17.2,132.6],[17.4,131.9],[17.5,131.4],[17.7,130.8],[17.9,130.4],[18.3,130],[18.6,129.4],[18.7,129],[18.7,128.9],[18.8,128.8],[19.4,128.5],[20,128.2],[20.5,127.6],[20.6,127.3],[20.7,127.2],[20.8,127.2],[20.8,127.1],[21.1,127.1],[21.3,127.1],[21.8,127],[22,126.9],[22.1,126.7],[22.3,126.5],[22.4,126.4],[22.6,126.2],[22.8,126.1],[22.9,126],[23.1,125.9],[23.3,125.7],[23.4,125.6],[23.6,125.4],[23.7,125.3],[23.8,125.1],[24,125],[24.2,125],[24.4,124.9],[24.8,124.8],[25,124.6],[25.3,124.5],[25.6,124.2],[25.8,124],[26.3,123.8],[26.5,123.5],[26.7,123.2],[26.8,123.2],[27.1,122.8],[27.1,122.4],[27.4,122.2],[27.5,121.9],[27.6,122],[28,121.2],[28.7,120.4],[29.2,119.8],[29.5,119.5],[30.7,119],[31.3,119],[31.3,118.4],[31.9,118.2],[32.3,118],[32.5,117.9],[33.2,117.9],[33.5,118],[33.9,118.1],[34.1,118.2],[34.6,118.2],[34.8,118.6]]},"center":[34.8,118.6],"galeWarningArea":{"center":[34.8,120.32],"radius":490780}},{"part":{"jp":"予報　１２時間後","en":"Forecast for 12 hours ahead"},"advancedHours":12,"validtime":{"JST":"2026-07-14T09:00:00+09:00","UTC":"2026-07-14T00:00:00Z"},"probabilityCircle":{"radius":64820,"tangent":[[[37.32,120.58],[34.8,118.6]],[[34.8,118.6],[36.52,121.62]]]},"center":[37,121.2]},{"part":{"jp":"予報　２４時間後","en":"Forecast for 24 hours ahead"},"advancedHours":24,"validtime":{"JST":"2026-07-14T21:00:00+09:00","UTC":"2026-07-14T12:00:00Z"},"probabilityCircle":{"radius":92600,"tangent":[[[40.08,123.92],[37.4,120.67]],[[36.54,121.65],[38.85,125.37]]]},"center":[39.5,124.7]},{"part":{"jp":"予報　４８時間後","en":"Forecast for 48 hours ahead"},"advancedHours":48,"validtime":{"JST":"2026-07-15T21:00:00+09:00","UTC":"2026-07-15T12:00:00Z"},"probabilityCircle":{"radius":212980,"tangent":[[[45.91,136.14],[40.2,124.11]],[[38.72,125.08],[42.51,138.53]]]},"center":[44.3,137.6]}],"spec":[{"part":"title","issue":{"JST":"2026-07-13T21:45:00+09:00","UTC":"2026-07-13T12:45:00Z"},"typhoonNumber":"2609","name":{"jp":"バービー","en":"Bavi"},"category":{"jp":"台風","en":"TS"}},{"part":{"jp":"実況","en":"Analysis"},"maximumWind":{"sustained":{"m/s":"18","kt":"35"},"gust":{"m/s":"25","kt":"50"}},"galeWarning":[{"area":"東","range":{"km":650,"nm":350}},{"area":"西","range":{"km":330,"nm":180}}],"advancedHours":0,"category":{"jp":"台風","en":"TS"},"scale":"-","intensity":"-","position":{"deg":[34.8,118.6],"dm":[[34,50],[118,35]],"accuracy":"ほぼ正確"},"location":"華北","course":"北北東","speed":{"km/h":"15","kt":"7"},"pressure":"992","validtime":{"JST":"2026-07-13T21:00:00+09:00","UTC":"2026-07-13T12:00:00Z"}},{"part":{"jp":"予報　１２時間後","en":"Forecast for 12 hours ahead"},"maximumWind":{"sustained":{"m/s":"18","kt":"35"},"gust":{"m/s":"25","kt":"50"}},"advancedHours":12,"category":{"jp":"台風","en":"TS"},"intensity":"-","position":{"deg":[37,121.2],"dm":[[37,0],[121,10]]},"probabilityCircleRadius":{"km":65,"nm":35},"location":"華北","course":"北東","speed":{"km/h":"30","kt":"15"},"pressure":"992","validtime":{"JST":"2026-07-14T09:00:00+09:00","UTC":"2026-07-14T00:00:00Z"}},{"part":{"jp":"予報　２４時間後","en":"Forecast for 24 hours ahead"},"maximumWind":{"sustained":{"m/s":"18","kt":"35"},"gust":{"m/s":"25","kt":"50"}},"advancedHours":24,"category":{"jp":"台風","en":"TS"},"intensity":"-","position":{"deg":[39.5,124.7],"dm":[[39,30],[124,40]]},"probabilityCircleRadius":{"km":95,"nm":50},"location":"黄海","course":"北東","speed":{"km/h":"35","kt":"19"},"pressure":"990","validtime":{"JST":"2026-07-14T21:00:00+09:00","UTC":"2026-07-14T12:00:00Z"}},{"part":{"jp":"予報　４８時間後","en":"Forecast for 48 hours ahead"},"maximumWind":{"sustained":{"m/s":"18","kt":"35"},"gust":{"m/s":"25","kt":"50"}},"advancedHours":48,"category":{"jp":"温帯低気圧","en":"LOW"},"intensity":"-","position":{"deg":[44.3,137.6],"dm":[[44,20],[137,35]]},"probabilityCircleRadius":{"km":210,"nm":115},"location":"日本海","course":"東北東","speed":{"km/h":"50","kt":"27"},"pressure":"990","validtime":{"JST":"2026-07-15T21:00:00+09:00","UTC":"2026-07-15T12:00:00Z"}}]}